quri_parts/openqasm/NOTICE
quri_parts/openqasm/__init__.py
quri_parts/openqasm/circuit/__init__.py
quri_parts/openqasm/py.typed
quri_parts_openqasm-17.0.0.dist-info/LICENSE
quri_parts_openqasm-17.0.0.dist-info/METADATA
quri_parts_openqasm-17.0.0.dist-info/WHEEL
quri_parts_openqasm-17.0.0.dist-info/RECORD
